<?xml version="1.0" encoding="UTF-8"?>
<states>

       <CAFETERIA>
              <introduction>YOU WAKE UP CAFETERIA</introduction>
              <r1>yes</r1>
              <r2>no</r2>
       </CAFETERIA>
       <LIBRARY>
              <introduction>LOOK AT ALL THESE BOOKS IN THE LIBRARY</introduction>
              <r1>yes</r1> 
              <r2>no</r2>
       </LIBRARY>
       <MUB>
              <introduction>THERE IS A LOT OF FUN STUFF IN THE MUB</introduction>
              <r1>yes</r1>
              <r2>no</r2>
       </MUB>

       
</states>
